feffery_maplibre/AddImages.py
feffery_maplibre/ArcLayer.py
feffery_maplibre/AttributionControl.py
feffery_maplibre/EaseTo.py
feffery_maplibre/FitBounds.py
feffery_maplibre/FlyTo.py
feffery_maplibre/Fragment.py
feffery_maplibre/FullscreenControl.py
feffery_maplibre/GeoJsonLayer.py
feffery_maplibre/GeolocateControl.py
feffery_maplibre/HandleRawMap.py
feffery_maplibre/HeatmapLayer.py
feffery_maplibre/JumpTo.py
feffery_maplibre/Layer.py
feffery_maplibre/LayerGroup.py
feffery_maplibre/MapContainer.py
feffery_maplibre/Marker.py
feffery_maplibre/NavigationControl.py
feffery_maplibre/PanBy.py
feffery_maplibre/PanTo.py
feffery_maplibre/Popup.py
feffery_maplibre/Resize.py
feffery_maplibre/RotateTo.py
feffery_maplibre/ScaleControl.py
feffery_maplibre/SortLayers.py
feffery_maplibre/Source.py
feffery_maplibre/SourceGroup.py
feffery_maplibre/Stop.py
feffery_maplibre/TerrainLayer.py
feffery_maplibre/ZoomIn.py
feffery_maplibre/ZoomOut.py
feffery_maplibre/ZoomTo.py
feffery_maplibre/__init__.py
feffery_maplibre/_imports_.py
feffery_maplibre/async-deck_gl_layers.js
feffery_maplibre/async-deck_gl_layers.js.map
feffery_maplibre/feffery_maplibre.min.js
feffery_maplibre/feffery_maplibre.min.js.map
feffery_maplibre/metadata.json
feffery_maplibre/package-info.json
feffery_maplibre-0.1.0.dist-info/licenses/LICENSE
feffery_maplibre-0.1.0.dist-info/METADATA
feffery_maplibre-0.1.0.dist-info/WHEEL
feffery_maplibre-0.1.0.dist-info/top_level.txt
feffery_maplibre-0.1.0.dist-info/RECORD
