Metadata-Version: 2.4
Name: feffery_maplibre
Version: 0.1.0
Summary: High performance map framework for Plotly Dash, based on maplibre and deck.gl.
Home-page: https://github.com/CNFeffery/feffery-maplibre
Author: CNFeffery <fefferypzy@gmail.com>
Author-email: fefferypzy@gmail.com
License: MIT
Classifier: Framework :: Dash
License-File: LICENSE
Requires-Dist: dash>=3.1.0
Dynamic: author
Dynamic: author-email
Dynamic: classifier
Dynamic: description-content-type
Dynamic: home-page
Dynamic: license
Dynamic: license-file
Dynamic: requires-dist
Dynamic: summary
